im_poster_telegram/__init__.py
im_poster_telegram/im_poster.py
im_botposter-0.0.4.dist-info/LICENSE
im_botposter-0.0.4.dist-info/METADATA
im_botposter-0.0.4.dist-info/WHEEL
im_botposter-0.0.4.dist-info/top_level.txt
im_botposter-0.0.4.dist-info/RECORD
