Metadata-Version: 2.1
Name: im-botposter
Version: 0.0.4
Summary: Im_poster is a Telegram Posts Management Tool
Home-page: https://github.com/Adiziel/Imposter
Author: Adiziel
Author-email: aditya.pathak.plus@gmail.com
License: UNKNOWN
Keywords: python,telegram,telegram bot
Platform: UNKNOWN
License-File: LICENSE
Requires-Dist: requests
Requires-Dist: json
